{"pools":[{"rolls":1,"entries":[{"type":"minecraft:item","name":"minecraft:stripped_oak_log","functions":[{"function":"minecraft:set_count","count":16}]}]},{"rolls":1,"entries":[{"type":"minecraft:item","name":"minecraft:prismarine_bricks","functions":[{"function":"minecraft:set_count","count":8}]}]},{"rolls":1,"entries":[{"type":"minecraft:item","name":"minecraft:acacia_fence_gate","functions":[{"function":"minecraft:set_count","count":16}]}]},{"rolls":1,"entries":[{"type":"minecraft:item","name":"minecraft:acacia_stairs","functions":[{"function":"minecraft:set_count","count":16}]}]},{"rolls":1,"entries":[{"type":"minecraft:item","name":"minecraft:smooth_stone","functions":[{"function":"minecraft:set_count","count":16}]}]},{"rolls":1,"entries":[{"type":"minecraft:item","name":"minecraft:andesite","functions":[{"function":"minecraft:set_count","count":16}]}]},{"rolls":1,"entries":[{"type":"minecraft:item","name":"minecraft:red_wool","functions":[{"function":"minecraft:set_count","count":16}]}]},{"rolls":1,"entries":[{"type":"minecraft:item","name":"minecraft:red_concrete","functions":[{"function":"minecraft:set_count","count":16}]}]},{"rolls":1,"entries":[{"type":"minecraft:item","name":"mineminenomi:belly_pouch","weight":100,"functions":[{"function":"mineminenomi:set_belly_in_pouch","belly_range":{"min":1500,"max":1500,"type":"minecraft:uniform"}}]}]},{"rolls":1,"entries":[{"type":"minecraft:item","name":"minecraft:acacia_door","functions":[{"function":"minecraft:set_count","count":4}]}]},{"rolls":1,"entries":[{"type":"minecraft:item","name":"minecraft:smooth_sandstone","functions":[{"function":"minecraft:set_count","count":16}]}]}]}